README.rst
setup.cfg
setup.py
avatica/__init__.py
avatica/client.py
avatica/connection.py
avatica/cursor.py
avatica/errors.py
avatica/types.py
avatica/proto/__init__.py
avatica/proto/common_pb2.py
avatica/proto/requests_pb2.py
avatica/proto/responses_pb2.py
avatica_python.egg-info/PKG-INFO
avatica_python.egg-info/SOURCES.txt
avatica_python.egg-info/dependency_links.txt
avatica_python.egg-info/requires.txt
avatica_python.egg-info/top_level.txt
examples/__init__.py
examples/superhirn_test.py