Metadata-Version: 1.1
Name: avatica-python
Version: 0.1
Summary: Avatica database adapter for Python
Home-page: https://bitbucket.org/lalinsky/python-phoenixdb
Author: wangyonghe
Author-email: yonghe.wang@joowing.com
License: Apache 2
Platform: UNKNOWN
Classifier: Programming Language :: Python
Classifier: Programming Language :: Python :: 2
Classifier: Programming Language :: Python :: 2.7
Classifier: Programming Language :: Python :: 3
Classifier: Programming Language :: Python :: 3.4
Classifier: Programming Language :: Python :: 3.5
Classifier: Programming Language :: Python :: 3.6
